{"milestoneTimings":[{"name":"Node started","timeSinceStartOrReload":0},{"name":"Splash screen displayed","timeSinceStartOrReload":244},{"name":"Initial render of foreground window","timeSinceStartOrReload":2734},{"name":"GitKraken loaded (Repo Tab)","timeSinceStartOrReload":5867}],"eventTimings":[{"name":"--- NO TRACKED EVENTS ---","relativeStart":0,"relativeEnd":75,"duration":75,"milestone":"GitKraken loaded (Repo Tab)"},{"name":"Critical mount behavior","relativeStart":75,"relativeEnd":540,"duration":465,"milestone":"GitKraken loaded (Repo Tab)"},{"name":"StartUpTrigger","relativeStart":76,"relativeEnd":680,"duration":604,"milestone":"GitKraken loaded (Repo Tab)"},{"name":"Opening repository","relativeStart":723,"relativeEnd":3133,"duration":2410,"milestone":"GitKraken loaded (Repo Tab)"},{"name":"refreshRepo","relativeStart":2343,"relativeEnd":2952,"duration":609,"milestone":"GitKraken loaded (Repo Tab)"},{"name":"opening renderer window","relativeStart":48,"relativeEnd":91,"duration":43,"milestone":"Initial render of foreground window"},{"name":"--- NO TRACKED EVENTS ---","relativeStart":91,"relativeEnd":515,"duration":424,"milestone":"Initial render of foreground window"},{"name":"loading style sheets","relativeStart":515,"relativeEnd":572,"duration":57,"milestone":"Initial render of foreground window"},{"name":"loading monaco scripts","relativeStart":572,"relativeEnd":1117,"duration":545,"milestone":"Initial render of foreground window"},{"name":"index.js pre-bootstrap","relativeStart":1117,"relativeEnd":1230,"duration":113,"milestone":"Initial render of foreground window"},{"name":"loading bootstrapScript and its imports","relativeStart":1230,"relativeEnd":1760,"duration":530,"milestone":"Initial render of foreground window"},{"name":"main.jsx pre-mount","relativeStart":1760,"relativeEnd":2490,"duration":730,"milestone":"Initial render of foreground window"},{"name":"first main.js require statements","relativeStart":0,"relativeEnd":12,"duration":12,"milestone":"Splash screen displayed"},{"name":"second main.js require statements","relativeStart":12,"relativeEnd":83,"duration":71,"milestone":"Splash screen displayed"},{"name":"main.js require yargs","relativeStart":83,"relativeEnd":85,"duration":2,"milestone":"Splash screen displayed"},{"name":"waiting for app ready","relativeStart":86,"relativeEnd":243,"duration":157,"milestone":"Splash screen displayed"}]}